__init__.py
pytorrents_csv/__init__.py
pytorrents_csv/pytorrents_csv.py
pytorrents_csv-2.0.1.dist-info/LICENSE
pytorrents_csv-2.0.1.dist-info/METADATA
pytorrents_csv-2.0.1.dist-info/WHEEL
pytorrents_csv-2.0.1.dist-info/entry_points.txt
pytorrents_csv-2.0.1.dist-info/top_level.txt
pytorrents_csv-2.0.1.dist-info/RECORD
