Metadata-Version: 2.2
Name: pytorrents-csv
Version: 2.0.1
Summary: a python cli client for torrents-csv
Author-email: mazer <contact@m3r.one>
Project-URL: Homepage, https://github.com/m3rone/pytorrents-csv
Project-URL: Bug Tracker, https://github.com/m3rone/pytorrents-csv/issues
Classifier: Programming Language :: Python :: 3
Classifier: License :: OSI Approved :: MIT License
Classifier: Operating System :: OS Independent
Requires-Python: >=3.10
License-File: LICENSE
Requires-Dist: certifi==2024.7.4
Requires-Dist: charset-normalizer==3.1.0
Requires-Dist: idna==3.7
Requires-Dist: requests==2.32.2
Requires-Dist: urllib3==1.26.19
